{
	"wifi": {
		"ssid": "<YOUR-WIFI-SSID>",
		"password": "<YOUR-WIFI-PASSWORD>"
	},
	"t6": {
		"scheme": "https://",
		"host": "api.internetcollaboratif.info",
		"port": 443,
		"servicesStatus": {
			"sockets": true,
			"mdns": true,
			"ssdp": true,
			"audio": true,
			"http": true
		},
		"t6Object_id": "<YOUR-T6-OBJECTID>",
		"t6ObjectSecretKey": "<YOUR-T6-OBJECT-SECRECT>",
		"websockets": {
			"host": "ws.internetcollaboratif.info",
			"port": 80,
			"path": "/",
			"t6wsKey": "<YOUR-T6-KEY>",
			"t6wsSecret": "<YOUR-T6-SECRECT>",
			"expiration": 1695124232506,
			"messageInterval": 15000,
			"messageIntervalOnceClaimed": 600000,
			"reconnectInterval": 5000,
			"timeoutInterval": 3000,
			"disconnectAfterFailure": 2
		},
		"mdns": {
			"localPort": 80
		},
		"http": {
			"localPort": 80,
			"localPortHTTPS": 443,
			"PARAM_INPUT_PIN": "pin",
			"PARAM_INPUT_VALUE": "value",
			"PARAM_INPUT_RESOLUTION": "resolution",
			"PARAM_INPUT_CHANNEL": "channel",
			"PARAM_INPUT_MODE": "mode"
		},
		"ssdp": {
			"localPort": 80,
			"advertiseInterval": 600,
			"presentationURL": "/",
			"friendlyName": "t6Object demo",
			"modelName": "t6 IoT",
			"modelNumber": "1.0.1",
			"deviceType": "upnp:rootdevice",
			"modelURL": "https://github.com/mathcoll/t6iot",
			"manufacturer": "Internet Collaboratif",
			"manufacturerURL": "https://www.internetcollaboratif.info"
		}
	}
}